{
  "restrictions": [
    {
      "type": "notempty",
      "message": "You must provide a value for the 'message' parameter",
      "types": [
        "msg"
      ]
    }
  ],
  "block": {
    "type": "delete_message",
    "message0": "delete message %1",
    "args0": [
      {
        "type": "input_value",
        "name": "msg",
        "check": "Message"
      }
    ],
    "inputsInline": false,
    "previousStatement": null,
    "nextStatement": null,
    "colour": 90,
    "tooltip": "Deletes a message",
    "helpUrl": ""
  },
  "generator": "_return = Blockly.JavaScript.valueToCode(block, 'msg', Blockly.JavaScript.ORDER_ATOMIC) + '.delete();'"
}